pydurable/__init__.py
pydurable/cli/__init__.py
pydurable/cli/apikey.py
pydurable/cli/aws.py
pydurable/cli/config.py
pydurable/cli/func.py
pydurable/cli/login.py
pydurable/cli/temporal.py
pydurable/entry_cli.py
pydurable/worker/__init__.py
pydurable/worker/client.py
pydurable/worker/interceptor.py
pydurable/worker/wait_for_exit.py
pydurable/worker/worker.py
pydurable-0.2.6.dist-info/METADATA
pydurable-0.2.6.dist-info/WHEEL
pydurable-0.2.6.dist-info/entry_points.txt
pydurable-0.2.6.dist-info/RECORD
