Metadata-Version: 2.1
Name: pydurable
Version: 0.2.6
Summary: 
Author: Dan Zilberman
Author-email: dan.zilberman99@gmail.com
Requires-Python: >=3.10,<4.0
Classifier: Programming Language :: Python :: 3
Classifier: Programming Language :: Python :: 3.10
Classifier: Programming Language :: Python :: 3.11
Classifier: Programming Language :: Python :: 3.12
Provides-Extra: cli
Requires-Dist: docker (>=7.0.0,<8.0.0) ; extra == "cli"
Requires-Dist: grpcio (>=1.60.0,<2.0.0)
Requires-Dist: requests (>=2.31.0,<3.0.0)
Requires-Dist: temporalio (>=1.5.0,<2.0.0) ; extra == "cli"
Requires-Dist: typer (>=0.9.0,<0.10.0) ; extra == "cli"
Requires-Dist: update (>=0.0.1,<0.0.2)
